LICENSE.txt
MANIFEST.in
README.md
setup.py
jk_packunpack/FileUncompressionGuess.py
jk_packunpack/Packer.py
jk_packunpack/Packer1.py
jk_packunpack/SpoolInfo.py
jk_packunpack/Spooler.py
jk_packunpack/Unpacker.py
jk_packunpack/Unpacker1.py
jk_packunpack/_NameMatcher.py
jk_packunpack/__init__.py
jk_packunpack.egg-info/PKG-INFO
jk_packunpack.egg-info/SOURCES.txt
jk_packunpack.egg-info/dependency_links.txt
jk_packunpack.egg-info/not-zip-safe
jk_packunpack.egg-info/requires.txt
jk_packunpack.egg-info/top_level.txt
jk_packunpack/impl/PosixExternalTar.py
jk_packunpack/impl/PythonNativeTar.py
jk_packunpack/impl/__init__.py