Metadata-Version: 2.1
Name: jk-packunpack
Version: 0.2022.10.25
Summary: Helper module to create or unpack tar archives, compress or uncompress files.
Home-page: UNKNOWN
Author: Jürgen Knauth
Author-email: pubsrc@binary-overflow.de
License: proprietary
Keywords: gz,gzip,tar,bz2,bzip,xz
Platform: UNKNOWN
Classifier: Development Status :: 4 - Beta
Classifier: Programming Language :: Python :: 3
